{
  "parameters": [

  ],
  "response_fields": [

  ],
  "requests": [
    {
      "request_headers": {
        "Content-Type": "application/x-www-form-urlencoded"
      },
      "request_query_parameters": {
      },
      "response_headers": {
        "X-Frame-Options": "SAMEORIGIN",
        "X-XSS-Protection": "1; mode=block",
        "X-Content-Type-Options": "nosniff",
        "X-Download-Options": "noopen",
        "X-Permitted-Cross-Domain-Policies": "none",
        "Referrer-Policy": "strict-origin-when-cross-origin",
        "X-Requested-With": "",
        "Vary": "X-Requested-With, X-Workarea-Segments",
        "Last-Modified": "Wed, 27 Nov 2019 00:06:58 GMT",
        "Cache-Control": "no-cache, no-store, must-revalidate",
        "X-Request-Id": "b249edbd-b293-4ff2-a919-770a594d7296",
        "X-Runtime": "0.021934",
        "X-Workarea-Segments": "",
        "Expires": "0"
      },
      "request_method": "DELETE",
      "request_path": "/api/admin/inventory_skus/SKU",
      "request_body": null,
      "request_content_type": "application/x-www-form-urlencoded",
      "response_status": 204,
      "response_status_text": "No Content",
      "response_body": null,
      "response_content_type": null,
      "curl": "curl \"https://www.example.com/api/admin/inventory_skus/SKU\" -d '' -X DELETE \\\n\t-H \"Content-Type: application/x-www-form-urlencoded\""
    }
  ],
  "resource": "Inventory SKUs",
  "description": "Removing an inventory SKU",
  "route": "/api/admin/inventory_skus/:id",
  "http_method": "DELETE"
}