{
  "parameters": [

  ],
  "response_fields": [

  ],
  "requests": [
    {
      "request_headers": {
        "Content-Type": "application/json"
      },
      "request_query_parameters": {
      },
      "response_headers": {
        "X-Frame-Options": "SAMEORIGIN",
        "X-XSS-Protection": "1; mode=block",
        "X-Content-Type-Options": "nosniff",
        "X-Download-Options": "noopen",
        "X-Permitted-Cross-Domain-Policies": "none",
        "Referrer-Policy": "strict-origin-when-cross-origin",
        "Cache-Control": "no-cache, no-store, must-revalidate",
        "X-Request-Id": "bb1d9f51-8c8b-46b2-a409-2b8795488c75",
        "X-Runtime": "0.025700",
        "Expires": "0"
      },
      "request_method": "PATCH",
      "request_path": "/api/admin/releases/5d5eca73d4322a04dfbf6dab",
      "request_body": "{\"created_at\":\"2019-08-22T17:01:39.330Z\",\"name\":\"Content Release\",\"publish_at\":null,\"publish_job_id\":null,\"published_at\":null,\"subscribed_user_ids\":[],\"tags\":[],\"undo_at\":null,\"undo_job_id\":null,\"undone_at\":null,\"updated_at\":\"2019-08-22T17:01:39.330Z\"}",
      "request_content_type": "application/json",
      "response_status": 204,
      "response_status_text": "No Content",
      "response_body": null,
      "response_content_type": null,
      "curl": "curl \"https://www.example.com/api/admin/releases/5d5eca73d4322a04dfbf6dab\" -d '{\"created_at\":\"2019-08-22T17:01:39.330Z\",\"name\":\"Content Release\",\"publish_at\":null,\"publish_job_id\":null,\"published_at\":null,\"subscribed_user_ids\":[],\"tags\":[],\"undo_at\":null,\"undo_job_id\":null,\"undone_at\":null,\"updated_at\":\"2019-08-22T17:01:39.330Z\"}' -X PATCH \\\n\t-H \"Content-Type: application/json\""
    }
  ],
  "resource": "Releases",
  "description": "Updating a release",
  "route": "/api/admin/releases/:id",
  "http_method": "PATCH"
}