{
  "parameters": [

  ],
  "response_fields": [

  ],
  "requests": [
    {
      "request_headers": {
        "Content-Type": "application/json"
      },
      "request_query_parameters": {
      },
      "response_headers": {
        "X-Frame-Options": "SAMEORIGIN",
        "X-XSS-Protection": "1; mode=block",
        "X-Content-Type-Options": "nosniff",
        "X-Download-Options": "noopen",
        "X-Permitted-Cross-Domain-Policies": "none",
        "Referrer-Policy": "strict-origin-when-cross-origin",
        "Cache-Control": "no-cache, no-store, must-revalidate",
        "X-Request-Id": "04f5d968-a022-423c-bd4f-33b3efc4d31f",
        "X-Runtime": "0.169656",
        "Expires": "0"
      },
      "request_method": "PATCH",
      "request_path": "/api/admin/pages/bulk",
      "request_body": "{\"pages\":[{\"active\":true,\"created_at\":\"2019-07-23T18:16:17.092Z\",\"display_h1\":true,\"name\":\"Test Page\",\"show_navigation\":false,\"subscribed_user_ids\":[],\"tags\":[],\"template\":\"generic\",\"updated_at\":\"2019-07-23T18:16:17.092Z\"},{\"active\":true,\"created_at\":\"2019-07-23T18:16:17.092Z\",\"display_h1\":true,\"name\":\"Test Page\",\"show_navigation\":false,\"subscribed_user_ids\":[],\"tags\":[],\"template\":\"generic\",\"updated_at\":\"2019-07-23T18:16:17.092Z\"},{\"active\":true,\"created_at\":\"2019-07-23T18:16:17.092Z\",\"display_h1\":true,\"name\":\"Test Page\",\"show_navigation\":false,\"subscribed_user_ids\":[],\"tags\":[],\"template\":\"generic\",\"updated_at\":\"2019-07-23T18:16:17.092Z\"}]}",
      "request_content_type": "application/json",
      "response_status": 204,
      "response_status_text": "No Content",
      "response_body": null,
      "response_content_type": null,
      "curl": "curl \"https://www.example.com/api/admin/pages/bulk\" -d '{\"pages\":[{\"active\":true,\"created_at\":\"2019-07-23T18:16:17.092Z\",\"display_h1\":true,\"name\":\"Test Page\",\"show_navigation\":false,\"subscribed_user_ids\":[],\"tags\":[],\"template\":\"generic\",\"updated_at\":\"2019-07-23T18:16:17.092Z\"},{\"active\":true,\"created_at\":\"2019-07-23T18:16:17.092Z\",\"display_h1\":true,\"name\":\"Test Page\",\"show_navigation\":false,\"subscribed_user_ids\":[],\"tags\":[],\"template\":\"generic\",\"updated_at\":\"2019-07-23T18:16:17.092Z\"},{\"active\":true,\"created_at\":\"2019-07-23T18:16:17.092Z\",\"display_h1\":true,\"name\":\"Test Page\",\"show_navigation\":false,\"subscribed_user_ids\":[],\"tags\":[],\"template\":\"generic\",\"updated_at\":\"2019-07-23T18:16:17.092Z\"}]}' -X PATCH \\\n\t-H \"Content-Type: application/json\""
    }
  ],
  "resource": "Pages",
  "description": "Bulk upserting pages",
  "route": "/api/admin/pages/bulk",
  "http_method": "PATCH"
}