{
  "parameters": [

  ],
  "response_fields": [

  ],
  "requests": [
    {
      "request_headers": {
        "Content-Type": "application/json"
      },
      "request_query_parameters": {
      },
      "response_headers": {
        "X-Frame-Options": "SAMEORIGIN",
        "X-XSS-Protection": "1; mode=block",
        "X-Content-Type-Options": "nosniff",
        "X-Download-Options": "noopen",
        "X-Permitted-Cross-Domain-Policies": "none",
        "Referrer-Policy": "strict-origin-when-cross-origin",
        "Cache-Control": "no-cache, no-store, must-revalidate",
        "X-Request-Id": "765252e5-6000-420d-8a31-011dff909e70",
        "X-Runtime": "0.026635",
        "Expires": "0"
      },
      "request_method": "DELETE",
      "request_path": "/api/admin/pages/5d5dbda8d4322a4b69d7939f",
      "request_body": null,
      "request_content_type": "application/json",
      "response_status": 204,
      "response_status_text": "No Content",
      "response_body": null,
      "response_content_type": null,
      "curl": "curl \"https://www.example.com/api/admin/pages/5d5dbda8d4322a4b69d7939f\" -d '' -X DELETE \\\n\t-H \"Content-Type: application/json\""
    }
  ],
  "resource": "Pages",
  "description": "Removing a page",
  "route": "/api/admin/pages/:id",
  "http_method": "DELETE"
}